ltspice_agent-0.1.1.dist-info/licenses/LICENSE
spiceagent/__init__.py
spiceagent/power_agent.py
spiceagent/resources/Buck_converter_real.asc
ltspice_agent-0.1.1.dist-info/METADATA
ltspice_agent-0.1.1.dist-info/WHEEL
ltspice_agent-0.1.1.dist-info/top_level.txt
ltspice_agent-0.1.1.dist-info/RECORD
