Metadata-Version: 2.4
Name: ltspice-agent
Version: 0.1.1
Summary: An AI-agent for optimization of power electronics circuits
Author-email: Davide Milillo <davidemichele2001@gmail.com>
License: MIT License
Project-URL: Homepage, https://github.com/DavideMilillo/SpiceAgent
Project-URL: Repository, https://github.com/DavideMilillo/SpiceAgent
Keywords: spice,optimization,ai,power electronics
Classifier: Development Status :: 3 - Alpha
Classifier: Intended Audience :: Science/Research
Classifier: Programming Language :: Python :: 3
Requires-Python: >=3.9
License-File: LICENSE
Requires-Dist: numpy
Requires-Dist: matplotlib
Requires-Dist: langchain
Requires-Dist: langchain-openai
Requires-Dist: langgraph
Requires-Dist: PyLTSpice
Dynamic: license-file
